bacli/__init__.py
bacli/cli.py
bacli/cli_legacy.py
bacli-1.0.dist-info/DESCRIPTION.rst
bacli-1.0.dist-info/METADATA
bacli-1.0.dist-info/RECORD
bacli-1.0.dist-info/WHEEL
bacli-1.0.dist-info/metadata.json
bacli-1.0.dist-info/top_level.txt
