Metadata-Version: 2.1
Name: bacli
Version: 1.0
Summary: Born Again Command Line Interface.
Home-page: https://github.com/JoeyDP/bacli
Author: Joey De Pauw
Author-email: joeydepauw@gmail.com
License: MIT
Platform: UNKNOWN
Classifier: Programming Language :: Python :: 3
Classifier: License :: OSI Approved :: MIT License
Classifier: Operating System :: OS Independent
